coordstometers/__init__.py
coordstometers-0.0.4.dist-info/LICENSE
coordstometers-0.0.4.dist-info/METADATA
coordstometers-0.0.4.dist-info/WHEEL
coordstometers-0.0.4.dist-info/top_level.txt
coordstometers-0.0.4.dist-info/RECORD
